metldata/__init__.py
metldata/py.typed
metldata/builtin_transformations/__init__.py
metldata/builtin_transformations/common/__init__.py
metldata/builtin_transformations/common/custom_types.py
metldata/builtin_transformations/common/utils.py
metldata/builtin_transformations/common/assumptions/__init__.py
metldata/builtin_transformations/common/assumptions/path_assumptions.py
metldata/builtin_transformations/common/path/__init__.py
metldata/builtin_transformations/common/path/path.py
metldata/builtin_transformations/common/path/path_elements.py
metldata/builtin_transformations/common/path/path_str.py
metldata/builtin_transformations/delete_class/__init__.py
metldata/builtin_transformations/delete_class/assumptions.py
metldata/builtin_transformations/delete_class/config.py
metldata/builtin_transformations/delete_class/data_transform.py
metldata/builtin_transformations/delete_class/main.py
metldata/builtin_transformations/delete_class/model_transform.py
metldata/builtin_transformations/duplicate_class/__init__.py
metldata/builtin_transformations/duplicate_class/assumptions.py
metldata/builtin_transformations/duplicate_class/config.py
metldata/builtin_transformations/duplicate_class/data_transform.py
metldata/builtin_transformations/duplicate_class/main.py
metldata/builtin_transformations/duplicate_class/model_transform.py
metldata/builtin_transformations/infer_relation/__init__.py
metldata/builtin_transformations/infer_relation/assumptions.py
metldata/builtin_transformations/infer_relation/config.py
metldata/builtin_transformations/infer_relation/data_transform.py
metldata/builtin_transformations/infer_relation/main.py
metldata/builtin_transformations/infer_relation/model_transform.py
metldata/builtin_transformations/infer_relation/resolve_path.py
metldata/builtin_transformations/merge_relations/__init__.py
metldata/builtin_transformations/merge_relations/assumptions.py
metldata/builtin_transformations/merge_relations/config.py
metldata-5.0.1.dist-info/licenses/LICENSE
metldata-5.0.1.dist-info/METADATA
metldata-5.0.1.dist-info/WHEEL
metldata-5.0.1.dist-info/top_level.txt
metldata-5.0.1.dist-info/RECORD
