Metadata-Version: 2.4
Name: metldata
Version: 5.0.1
Summary: metldata - A framework for handling metadata based on ETL, CQRS, and event sourcing.
Author-email: "German Human Genome Phenome Archive (GHGA)" <contact@ghga.de>
License: Apache 2.0
Project-URL: Repository, https://github.com/ghga-de/hexkit
Classifier: Development Status :: 5 - Production/Stable
Classifier: Operating System :: POSIX :: Linux
Classifier: Programming Language :: Python :: 3
Classifier: Programming Language :: Python :: 3.13
Classifier: License :: OSI Approved :: Apache Software License
Classifier: Topic :: Internet :: WWW/HTTP :: HTTP Servers
Classifier: Topic :: Software Development :: Libraries
Classifier: Intended Audience :: Developers
Requires-Python: >=3.13
License-File: LICENSE
Requires-Dist: schemapack<5,>=4
Requires-Dist: jinja2<4,>=3
Dynamic: license-file
